models/__init__.py
models/auggan/__init__.py
models/difgan/__init__.py
models/difgan/diffusion.py
models/nn_common/__init__.py
models/nn_common/discriminator.py
models/nn_common/generator.py
stgan-0.2.dist-info/licenses/LICENSE
stgan-0.2.dist-info/METADATA
stgan-0.2.dist-info/WHEEL
stgan-0.2.dist-info/entry_points.txt
stgan-0.2.dist-info/top_level.txt
stgan-0.2.dist-info/RECORD
