Metadata-Version: 2.4
Name: stgan
Version: 0.2
Summary: A Python package to simulate spatial transcriptomic datasets from few training examples.
Author: George Hall, Leilani Hoffmann
License: MIT License
Requires-Python: >=3.8
License-File: LICENSE
Requires-Dist: torch==2.6.0
Requires-Dist: torchvision==0.21.0
Requires-Dist: numpy==2.1.2
Requires-Dist: pandas==2.3.1
Requires-Dist: matplotlib>=3.5
Requires-Dist: ipython>=8.0
Requires-Dist: pillow==11.0.0
Dynamic: license-file
